tokamesh/__init__.py
tokamesh/_version.py
tokamesh/construction.py
tokamesh/diagnostics.py
tokamesh/geometry.py
tokamesh/intersection.py
tokamesh/mesh.py
tokamesh/operators.py
tokamesh/utilities.py
tokamesh/tokamaks/__init__.py
tokamesh/tokamaks/mastu_boundary_data.npz
tokamesh-0.5.4.dist-info/licenses/LICENSE
tokamesh-0.5.4.dist-info/METADATA
tokamesh-0.5.4.dist-info/WHEEL
tokamesh-0.5.4.dist-info/top_level.txt
tokamesh-0.5.4.dist-info/RECORD
