Metadata-Version: 2.4
Name: tokamesh
Version: 0.5.4
Summary: Python tools for constructing meshes and geometry matrices used in tomography problems
Author-email: Chris Bowman <chris.bowman.physics@gmail.com>
License: MIT License
Project-URL: Homepage, https://github.com/C-bowman/tokamesh
Project-URL: Source, https://github.com/C-bowman/tokamesh
Project-URL: Tracker, https://github.com/C-bowman/tokamesh/issues
Project-URL: Documentation, https://tokamesh.readthedocs.io/en/stable/
Classifier: Programming Language :: Python :: 3
Classifier: License :: OSI Approved :: MIT License
Classifier: Operating System :: OS Independent
Requires-Python: >=3.9
License-File: LICENSE
Requires-Dist: numpy>=1.24.4
Requires-Dist: scipy>=1.10.1
Requires-Dist: matplotlib>=3.5.3
Provides-Extra: tests
Requires-Dist: pytest>=3.3.0; extra == "tests"
Requires-Dist: pytest-cov>=3.0.0; extra == "tests"
Requires-Dist: hypothesis>=6.24; extra == "tests"
Requires-Dist: triangle>=20230923; extra == "tests"
Provides-Extra: triangle
Requires-Dist: triangle>=20230923; extra == "triangle"
Dynamic: license-file
